LICENSE
MANIFEST.in
README.md
setup.py
autoplanner/__init__.py
autoplanner/admin.py
autoplanner/defaults.py
autoplanner/forms.py
autoplanner/iniconf.py
autoplanner/models.py
autoplanner/root_urls.py
autoplanner/schedule.py
autoplanner/signals.py
autoplanner/tasks.py
autoplanner/urls.py
autoplanner/utils.py
autoplanner/views.py
autoplanner.egg-info/PKG-INFO
autoplanner.egg-info/SOURCES.txt
autoplanner.egg-info/dependency_links.txt
autoplanner.egg-info/entry_points.txt
autoplanner.egg-info/not-zip-safe
autoplanner.egg-info/requires.txt
autoplanner.egg-info/top_level.txt
autoplanner/__pycache__/__init__.cpython-36.pyc
autoplanner/__pycache__/admin.cpython-36.pyc
autoplanner/__pycache__/defaults.cpython-36.pyc
autoplanner/__pycache__/forms.cpython-36.pyc
autoplanner/__pycache__/iniconf.cpython-36.pyc
autoplanner/__pycache__/models.cpython-36.pyc
autoplanner/__pycache__/root_urls.cpython-36.pyc
autoplanner/__pycache__/schedule.cpython-36.pyc
autoplanner/__pycache__/signals.cpython-36.pyc
autoplanner/__pycache__/tasks.cpython-36.pyc
autoplanner/__pycache__/urls.cpython-36.pyc
autoplanner/__pycache__/utils.cpython-36.pyc
autoplanner/__pycache__/views.cpython-36.pyc
autoplanner/migrations/0001_initial.py
autoplanner/migrations/0002_auto_20170903_2258.py
autoplanner/migrations/0003_auto_20170903_2337.py
autoplanner/migrations/0004_auto_20170904_0749.py
autoplanner/migrations/__init__.py
autoplanner/migrations/__pycache__/0001_initial.cpython-36.pyc
autoplanner/migrations/__pycache__/0002_auto_20170903_2258.cpython-36.pyc
autoplanner/migrations/__pycache__/0003_auto_20170903_2337.cpython-36.pyc
autoplanner/migrations/__pycache__/0004_auto_20170904_0749.cpython-36.pyc
autoplanner/migrations/__pycache__/__init__.cpython-36.pyc
autoplanner/static/admin/js/jquery.min.js
autoplanner/static/autoplanner/css/autoplanner.css
autoplanner/static/autoplanner/css/css/calendar.css
autoplanner/static/autoplanner/css/css/calendar.min.css
autoplanner/static/autoplanner/dev/doc/source/_static/logo.png
autoplanner/static/autoplanner/js/autoplanner.js
autoplanner/static/autoplanner/js/calendar.js
autoplanner/static/autoplanner/js/calendar.min.js
autoplanner/static/autoplanner/js/language/ar-SA.js
