Metadata-Version: 1.1
Name: autoplanner
Version: 0.9.7
Summary: No description yet.
Home-page: http://autoplanner.readthedocs.org/en/latest/
Author: Matthieu Gallet
Author-email: matthieu.gallet@19pouces.net
License: CeCILL-B
Platform: UNKNOWN
Classifier: Development Status :: 5 - Production/Stable
Classifier: Framework :: Django :: 1.11
Classifier: Framework :: Django :: 2.0
Classifier: Natural Language :: English
Classifier: Natural Language :: French
Classifier: Operating System :: MacOS :: MacOS X
Classifier: Operating System :: POSIX :: BSD
Classifier: Operating System :: POSIX :: Linux
Classifier: Operating System :: Unix
Classifier: License :: OSI Approved :: CEA CNRS Inria Logiciel Libre License, version 2.1 (CeCILL-2.1)
Classifier: Programming Language :: Python :: 3.5
Classifier: Programming Language :: Python :: 3.6
Classifier: Programming Language :: Python :: 3.7
Classifier: Programming Language :: Python :: 3 :: Only
